ufoProcessor/__init__.py
ufoProcessor/_version.py
ufoProcessor/emptyPen.py
ufoProcessor/logger.py
ufoProcessor/ufoOperator.py
ufoProcessor/varModels.py
ufoProcessor-1.13.2.dist-info/LICENSE
ufoProcessor-1.13.2.dist-info/METADATA
ufoProcessor-1.13.2.dist-info/WHEEL
ufoProcessor-1.13.2.dist-info/top_level.txt
ufoProcessor-1.13.2.dist-info/RECORD
