Metadata-Version: 2.1
Name: ufoProcessor
Version: 1.13.2
Summary: Read, write and generate UFOs with designspace data.
Home-page: https://github.com/LettError/ufoProcessor
Author: Erik van Blokland
Author-email: erik@letterror.com
License: MIT
Keywords: font development tools
Classifier: Development Status :: 4 - Beta
Classifier: Environment :: Console
Classifier: Environment :: Other Environment
Classifier: Intended Audience :: Developers
Classifier: Intended Audience :: End Users/Desktop
Classifier: License :: OSI Approved :: MIT License
Classifier: Natural Language :: English
Classifier: Operating System :: OS Independent
Classifier: Programming Language :: Python
Classifier: Programming Language :: Python :: 2
Classifier: Programming Language :: Python :: 3
Classifier: Topic :: Multimedia :: Graphics
Classifier: Topic :: Multimedia :: Graphics :: Graphics Conversion
Classifier: Topic :: Multimedia :: Graphics :: Editors :: Vector-Based
Classifier: Topic :: Software Development :: Libraries :: Python Modules
Requires-Python: >=2.7
License-File: LICENSE
Requires-Dist: defcon[lxml]>=0.6.0
Requires-Dist: fontMath>=0.4.9
Requires-Dist: fontParts>=0.8.2
Requires-Dist: fontTools[lxml,ufo]>=3.32.0
Requires-Dist: mutatorMath>=2.1.2
